linkedlist/__init__.py
linkedlist/linkedlist.py
LinkedList_utils_version_1-0.1.0.dist-info/LICENSE
LinkedList_utils_version_1-0.1.0.dist-info/METADATA
LinkedList_utils_version_1-0.1.0.dist-info/WHEEL
LinkedList_utils_version_1-0.1.0.dist-info/top_level.txt
LinkedList_utils_version_1-0.1.0.dist-info/RECORD
