Metadata-Version: 2.1
Name: LinkedList-utils-version-1
Version: 0.1.0
Summary: A powerful custom LinkedList implementation with advanced methods.
Home-page: https://github.com/Adhithya200503/LinkedList/blob/main/linkedList.py
Author: Adhithya S
Author-email: adhithya.s.200503@gmail.com
License: UNKNOWN
Platform: UNKNOWN
Classifier: Programming Language :: Python :: 3
Classifier: License :: OSI Approved :: MIT License
Classifier: Operating System :: OS Independent
Requires-Python: >=3.7
License-File: LICENSE
